README.md
license.txt
setup.cfg
setup.py
SmartHackerTools/__init__.py
SmartHackerTools/main.py
SmartHackerTools.egg-info/PKG-INFO
SmartHackerTools.egg-info/SOURCES.txt
SmartHackerTools.egg-info/dependency_links.txt
SmartHackerTools.egg-info/requires.txt
SmartHackerTools.egg-info/top_level.txt