Metadata-Version: 2.1
Name: SmartHackerTools
Version: 0.1
Summary: These contain some smart hacker tools!
Home-page: https://github.com/IndentationOrELSE
Download-URL: https://github.com/IndentationOrELSE/SmartHackerTools/archive/refs/tags/v_01.tar.gz
Author: Smart_Hacker
Author-email: sarthakmishra2100@gmail.com
License: MIT
Keywords: Tools,Simple,Beginner
Classifier: Development Status :: 3 - Alpha
Classifier: Intended Audience :: Developers
Classifier: Topic :: Software Development :: Build Tools
Classifier: License :: OSI Approved :: MIT License
Classifier: Programming Language :: Python :: 3
Classifier: Programming Language :: Python :: 3.4
Classifier: Programming Language :: Python :: 3.5
Classifier: Programming Language :: Python :: 3.6
Classifier: Programming Language :: Python :: 3.7
Classifier: Programming Language :: Python :: 3.8
Classifier: Programming Language :: Python :: 3.9
Classifier: Programming Language :: Python :: 3.10
Classifier: Programming Language :: Python :: 3.11
License-File: license.txt
